keepasxcli_wrapper/__init__.py
keepasxcli_wrapper/client.py
keepasxcli_wrapper/gui.py
keepasxcli_wrapper/server.py
keepasxcli_wrapper-0.1.7.dist-info/entry_points.txt
keepasxcli_wrapper-0.1.7.dist-info/WHEEL
keepasxcli_wrapper-0.1.7.dist-info/METADATA
keepasxcli_wrapper-0.1.7.dist-info/RECORD
