Metadata-Version: 2.1
Name: keepasxcli-wrapper
Version: 0.1.7
Summary: Wrapper arround keepassxc-cli open command.
Home-page: https://github.com/dburton90/keepasssxcli-wrapper
License: MIT
Keywords: keepassxc,keepassxci-cli
Author: Daniel Barton
Author-email: daniel.barton@seznam.cz
Requires-Python: >=3.8,<4.0
Classifier: License :: OSI Approved :: MIT License
Classifier: Programming Language :: Python :: 3
Classifier: Programming Language :: Python :: 3.8
Classifier: Programming Language :: Python :: 3.9
Requires-Dist: click (>=7.1.2,<8.0.0)
Requires-Dist: pexpect (>=4.8.0,<5.0.0)
